sdmdata/__init__.py
sdmdata/gbif.py
sdmdata/inaturalist.py
sdmdata/occurrence_requests.py
sdmdata/speciesLink.py
sdmdata-0.1.1.dist-info/licenses/LICENSE
sdmdata-0.1.1.dist-info/METADATA
sdmdata-0.1.1.dist-info/WHEEL
sdmdata-0.1.1.dist-info/top_level.txt
sdmdata-0.1.1.dist-info/RECORD
