Metadata-Version: 2.4
Name: sdmdata
Version: 0.1.1
Summary: A library for Species Distribution Modeling data retrieval from GBIF, iNaturalist, and SpeciesLink APIs.
Author: Ane Simões
Author-email: anes.2017@alunos.utfpr.edu.br
License: MIT
Requires-Python: >=3.7
License-File: LICENSE
Requires-Dist: pytest
Requires-Dist: pandas
Requires-Dist: requests
Requires-Dist: python-dotenv
Requires-Dist: pygbif
Requires-Dist: pyinaturalist
Dynamic: author
Dynamic: author-email
Dynamic: description
Dynamic: description-content-type
Dynamic: license
Dynamic: license-file
Dynamic: requires-dist
Dynamic: requires-python
Dynamic: summary
